throttle_controller/__init__.py
throttle_controller/_version.py
throttle_controller/protocol.py
throttle_controller/py.typed
throttle_controller/simple.py
throttle_controller/utils/__init__.py
throttle_controller/utils/interval.py
throttle_controller-0.3.1.dist-info/LICENSE
throttle_controller-0.3.1.dist-info/METADATA
throttle_controller-0.3.1.dist-info/WHEEL
throttle_controller-0.3.1.dist-info/top_level.txt
throttle_controller-0.3.1.dist-info/RECORD
