Metadata-Version: 2.2
Name: throttle-controller
Version: 0.3.1
Summary: A simple throttling controller
Author-email: Yui KITSU <kitsuyui+github@kitsuyui.com>
License: Copyright 2022-2025 Kitsu Yui
Project-URL: Homepage, https://github.com/kitsuyui/python-throttle-controller
Classifier: Development Status :: 3 - Alpha
Classifier: License :: OSI Approved :: BSD License
Classifier: Programming Language :: Python :: 3.9
Classifier: Programming Language :: Python :: 3.10
Classifier: Programming Language :: Python :: 3.11
Classifier: Programming Language :: Python :: 3.12
Classifier: Programming Language :: Python :: 3.13
Classifier: Intended Audience :: Developers
Requires-Python: >=3.9
License-File: LICENSE
Requires-Dist: typing-extensions
